microchain/__init__.py
microchain/functions.py
microchain/engine/__init__.py
microchain/engine/agent.py
microchain/engine/engine.py
microchain/engine/function.py
microchain/models/__init__.py
microchain/models/llama_generators.py
microchain/models/llm.py
microchain/models/openai_generators.py
microchain/models/templates.py
microchain/models/token_tracker.py
microchain_python-0.4.6.dist-info/LICENSE
microchain_python-0.4.6.dist-info/METADATA
microchain_python-0.4.6.dist-info/WHEEL
microchain_python-0.4.6.dist-info/top_level.txt
microchain_python-0.4.6.dist-info/RECORD
