Metadata-Version: 2.1
Name: microchain-python
Version: 0.4.6
Home-page: 
Author: Federico A. Galatolo
Author-email: federico.galatolo@unipi.it
Classifier: Programming Language :: Python :: 3.11
Classifier: License :: OSI Approved :: Apache Software License
Classifier: Operating System :: OS Independent
Classifier: Development Status :: 4 - Beta
License-File: LICENSE
Requires-Dist: termcolor ==2.4.0
Requires-Dist: pydantic <3,>=2
